GeoTesuario/Migration.py
GeoTesuario/SkosMigration.py
GeoTesuario/__init__.py
geotesuario-1.0.0.dist-info/licenses/LICENSE
geotesuario-1.0.0.dist-info/METADATA
geotesuario-1.0.0.dist-info/WHEEL
geotesuario-1.0.0.dist-info/top_level.txt
geotesuario-1.0.0.dist-info/RECORD
