Metadata-Version: 2.4
Name: GeoTesuario
Version: 1.0.0
Summary: Biblioteca para la migración de datos de GeoNames a vocabularios controlados en formato SKOS y texto etiquetado. Garantiza la generacion de archivos JSON, CSV con los datos completos de los lugares de geonames segun se le pase un txt con los datos en crudo que proprociona GeoNames. Tambien los puede exportar a formato de texto etuiquetado y rdf:skos para poder importar los loguares y sus nombres alternativos a un vocabulario controlado como por ejemplo TemaTres
Home-page: https://github.com/Yorjandy/geo_tesuario.git
Author: Yorjandy Martínez Lamas
Author-email: yorjandy5@gmail.com
Classifier: Programming Language :: Python :: 3
Classifier: License :: OSI Approved :: MIT License
Classifier: Operating System :: OS Independent
Requires-Python: >=3.6
License-File: LICENSE
Dynamic: author
Dynamic: author-email
Dynamic: classifier
Dynamic: description
Dynamic: description-content-type
Dynamic: home-page
Dynamic: license-file
Dynamic: requires-python
Dynamic: summary
